bluesky_tiled_plugins/__init__.py
bluesky_tiled_plugins/_version.py
bluesky_tiled_plugins/exporters.py
bluesky_tiled_plugins/queries.py
bluesky_tiled_plugins/utils.py
bluesky_tiled_plugins/clients/__init__.py
bluesky_tiled_plugins/clients/_common.py
bluesky_tiled_plugins/clients/bluesky_event_stream.py
bluesky_tiled_plugins/clients/bluesky_run.py
bluesky_tiled_plugins/clients/catalog_of_bluesky_runs.py
bluesky_tiled_plugins/clients/document.py
bluesky_tiled_plugins/writing/__init__.py
bluesky_tiled_plugins/writing/_dispatcher.py
bluesky_tiled_plugins/writing/_json_writer.py
bluesky_tiled_plugins/writing/consolidators.py
bluesky_tiled_plugins/writing/tiled_writer.py
bluesky_tiled_plugins/writing/validator.py
bluesky_tiled_plugins-2.0.1.dist-info/METADATA
bluesky_tiled_plugins-2.0.1.dist-info/WHEEL
bluesky_tiled_plugins-2.0.1.dist-info/entry_points.txt
bluesky_tiled_plugins-2.0.1.dist-info/RECORD
