Metadata-Version: 2.4
Name: bluesky-tiled-plugins
Version: 2.0.1
Summary: Integrations for using Tiled with Bluesky
Project-URL: Homepage, https://github.com/bluesky/bluesky-tiled-plugins
Project-URL: Bug Tracker, https://github.com/bluesky/bluesky-tiled-plugins/issues
Project-URL: Discussions, https://github.com/bluesky/bluesky-tiled-plugins/discussions
Project-URL: Changelog, https://github.com/bluesky/bluesky-tiled-plugins/releases
Author-email: Bluesky Project Contributors <dallan@bnl.gov>
Maintainer-email: Brookhaven National Laboratory <dallan@bnl.gov>
License-Expression: BSD-3-Clause
Classifier: Development Status :: 1 - Planning
Classifier: Intended Audience :: Developers
Classifier: Intended Audience :: Science/Research
Classifier: Operating System :: OS Independent
Classifier: Programming Language :: Python
Classifier: Programming Language :: Python :: 3
Classifier: Programming Language :: Python :: 3 :: Only
Classifier: Programming Language :: Python :: 3.10
Classifier: Programming Language :: Python :: 3.11
Classifier: Programming Language :: Python :: 3.12
Classifier: Programming Language :: Python :: 3.13
Classifier: Programming Language :: Python :: 3.14
Classifier: Topic :: Scientific/Engineering
Classifier: Typing :: Typed
Requires-Python: >=3.10
Requires-Dist: dask
Requires-Dist: event-model
Requires-Dist: mongoquery
Requires-Dist: pytz
Requires-Dist: tiled[client]>=0.2.0
Requires-Dist: tzlocal
